flerovium.py
src/__init__.py
src/db.py
src/file_helper.py
src/helper.py
src/html.py
src/image_compare.py
src/image_text.py
flerovium-0.0.1.dist-info/METADATA
flerovium-0.0.1.dist-info/WHEEL
flerovium-0.0.1.dist-info/entry_points.txt
flerovium-0.0.1.dist-info/top_level.txt
flerovium-0.0.1.dist-info/zip-safe
flerovium-0.0.1.dist-info/RECORD
