Metadata-Version: 2.1
Name: flerovium
Version: 0.0.1
Summary: find_by_label
Home-page: https://github.com/serialbandicoot/flerovium
Author: Sam Treweek
Author-email: samtreweek@gmail.com
License: MIT
Project-URL: Source code, https://github.com/serialbandicoot/flerovium
Project-URL: Issue tracker, https://github.com/serialbandicoot/flerovium/issues
Keywords: timezone
Platform: UNKNOWN
Classifier: Development Status :: 5 - Production/Stable
Classifier: License :: OSI Approved :: MIT License
Classifier: Operating System :: Microsoft :: Windows
Classifier: Operating System :: Unix
Classifier: Operating System :: MacOS :: MacOS X
Classifier: Programming Language :: Python :: 3.7
Requires-Python: >= 3.6
Provides-Extra: devenv
Requires-Dist: pytest-cov ; extra == 'devenv'
Requires-Dist: black ; extra == 'devenv'
Requires-Dist: pyroma ; extra == 'devenv'
Requires-Dist: zest.releaser ; extra == 'devenv'
Provides-Extra: test
Requires-Dist: pytest (>=4.3) ; extra == 'test'
